image_pattern/__init__.py
image_pattern/context.py
image_pattern/contrib/__init__.py
image_pattern/contrib/django.py
image_pattern/elements/__init__.py
image_pattern/elements/base.py
image_pattern/elements/canvas.py
image_pattern/elements/rectangle.py
image_pattern/elements/text.py
image_pattern/layers.py
image_pattern/patterns.py
image_pattern/size.py
image_pattern-0.0.18.dist-info/LICENSE
image_pattern-0.0.18.dist-info/WHEEL
image_pattern-0.0.18.dist-info/METADATA
image_pattern-0.0.18.dist-info/RECORD
