Metadata-Version: 2.1
Name: image-pattern
Version: 0.0.18
Summary: Package for creating images, such as social media sharing images and avatars, from declarative templates.
Home-page: https://github.com/brogency/image-pattern
License: MIT
Keywords: image,pattern,create,media,sharing
Author: acrius
Author-email: acrius@mail.ru
Requires-Python: >=3.7,<4.0
Classifier: Environment :: Web Environment
Classifier: Framework :: Django
Classifier: License :: OSI Approved :: MIT License
Classifier: Programming Language :: Python :: 3
Classifier: Programming Language :: Python :: 3.7
Requires-Dist: pillow (>=7.0,<8.0)
Requires-Dist: pydantic (>=1.4,<2.0)
Project-URL: Documentation, https://github.com/brogency/image-pattern
Project-URL: Repository, https://github.com/brogency/image-pattern
